{
    "id": "722e0fbf-58e4-4aa0-a25d-0402f0e1c701",
    "link": "https://ballchasing.com/api/replays/722e0fbf-58e4-4aa0-a25d-0402f0e1c701",
    "created": "2025-04-25T00:36:03.43363Z",
    "uploader": {
        "steam_id": "76561198419715376",
        "name": "polar",
        "profile_url": "https://steamcommunity.com/id/Kingcharlesviii/",
        "avatar": "https://avatars.steamstatic.com/55719c419beac7178c3b6fcee74281e9cdd69ca2.jpg"
    },
    "status": "ok",
    "rocket_league_id": "D18E3DD340DFE2DEDB530487E33A115F",
    "match_guid": "63748C8011F0216C8E7B02BF85745828",
    "title": "2025-04-24.19.36 polar Private Win",
    "map_code": "eurostadium_dusk_p",
    "match_type": "Private",
    "team_size": 3,
    "playlist_id": "private",
    "duration": 346,
    "overtime": false,
    "season": 18,
    "season_type": "free2play",
    "date": "2025-04-24T19:36:00-05:00",
    "date_has_timezone": true,
    "visibility": "public",
    "blue": {
        "color": "blue",
        "players": [
            {
                "start_time": 0,
                "end_time": 346.97595,
                "name": "nex.",
                "id": {
                    "platform": "steam",
                    "id": "76561198202714123"
                },
                "mvp": true,
                "car_id": 4284,
                "car_name": "Fennec",
                "camera": {
                    "fov": 110,
                    "height": 100,
                    "pitch": -3,
                    "distance": 280,
                    "stiffness": 0.35,
                    "swivel_speed": 5.3,
                    "transition_speed": 1.6
                },
                "steering_sensitivity": 2,
                "stats": {
                    "core": {
                        "shots": 4,
                        "shots_against": 4,
                        "goals": 2,
                        "goals_against": 0,
                        "saves": 2,
                        "assists": 0,
                        "score": 558,
                        "mvp": true,
                        "shooting_percentage": 50
                    },
                    "boost": {
                        "bpm": 378,
                        "bcpm": 398.1805,
                        "avg_amount": 45.19,
                        "amount_collected": 2203,
                        "amount_stolen": 451,
                        "amount_collected_big": 1663,
                        "amount_stolen_big": 200,
                        "amount_collected_small": 540,
                        "amount_stolen_small": 251,
                        "count_collected_big": 19,
                        "count_stolen_big": 2,
                        "count_collected_small": 50,
                        "count_stolen_small": 22,
                        "amount_overfill": 270,
                        "amount_overfill_stolen": 13,
                        "amount_used_while_supersonic": 244,
                        "time_zero_boost": 32.36,
                        "percent_zero_boost": 9.748162,
                        "time_full_boost": 73.77,
                        "percent_full_boost": 22.222555,
                        "time_boost_0_25": 96.27,
                        "time_boost_25_50": 75.85,
                        "time_boost_50_75": 73.87,
                        "time_boost_75_100": 87.87,
                        "percent_boost_0_25": 28.835442,
                        "percent_boost_25_50": 22.719105,
                        "percent_boost_50_75": 22.126043,
                        "percent_boost_75_100": 26.319416
                    },
                    "movement": {
                        "avg_speed": 1699,
                        "total_distance": 546804,
                        "time_supersonic_speed": 77.46,
                        "time_boost_speed": 152.37,
                        "time_slow_speed": 110.7,
                        "time_ground": 141.09,
                        "time_low_air": 171.28,
                        "time_high_air": 28.16,
                        "time_powerslide": 4.36,
                        "count_powerslide": 38,
                        "avg_powerslide_duration": 0.11,
                        "avg_speed_percentage": 73.86957,
                        "percent_slow_speed": 32.50815,
                        "percent_boost_speed": 44.744957,
                        "percent_supersonic_speed": 22.746895,
                        "percent_ground": 41.432472,
                        "percent_low_air": 50.298065,
                        "percent_high_air": 8.269463
                    },
                    "positioning": {
                        "avg_distance_to_ball": 2834,
                        "avg_distance_to_ball_possession": 2450,
                        "avg_distance_to_ball_no_possession": 3297,
                        "avg_distance_to_mates": 3951,
                        "time_defensive_third": 164.32,
                        "time_neutral_third": 97.13,
                        "time_offensive_third": 79.08,
                        "time_defensive_half": 219.7,
                        "time_offensive_half": 120.83,
                        "time_behind_ball": 262.48,
                        "time_infront_ball": 78.05,
                        "time_most_back": 116.9,
                        "time_most_forward": 103.6,
                        "time_closest_to_ball": 125.5,
                        "time_farthest_from_ball": 122.3,
                        "percent_defensive_third": 48.254192,
                        "percent_offensive_third": 23.222624,
                        "percent_neutral_third": 28.523184,
                        "percent_defensive_half": 64.517075,
                        "percent_offensive_half": 35.482925,
                        "percent_behind_ball": 77.07984,
                        "percent_infront_ball": 22.920153,
                        "percent_most_back": 35.215088,
                        "percent_most_forward": 31.20858,
                        "percent_closest_to_ball": 37.80576,
                        "percent_farthest_from_ball": 36.84179
                    },
                    "demo": {
                        "inflicted": 2,
                        "taken": 2
                    }
                }
            },
            {
                "start_time": 0,
                "end_time": 346.97595,
                "name": "polar",
                "id": {
                    "platform": "steam",
                    "id": "76561198419715376"
                },
                "car_id": 4284,
                "car_name": "Fennec",
                "camera": {
                    "fov": 110,
                    "height": 100,
                    "pitch": -5,
                    "distance": 270,
                    "stiffness": 0.4,
                    "swivel_speed": 3.5,
                    "transition_speed": 1.1
                },
                "steering_sensitivity": 1.7,
                "stats": {
                    "core": {
                        "shots": 4,
                        "shots_against": 4,
                        "goals": 2,
                        "goals_against": 0,
                        "saves": 0,
                        "assists": 1,
                        "score": 420,
                        "mvp": false,
                        "shooting_percentage": 50
                    },
                    "boost": {
                        "bpm": 341,
                        "bcpm": 351.5484,
                        "avg_amount": 44.56,
                        "amount_collected": 1945,
                        "amount_stolen": 466,
                        "amount_collected_big": 1219,
                        "amount_stolen_big": 334,
                        "amount_collected_small": 726,
                        "amount_stolen_small": 132,
                        "count_collected_big": 18,
                        "count_stolen_big": 4,
                        "count_collected_small": 62,
                        "count_stolen_small": 11,
                        "amount_overfill": 426,
                        "amount_overfill_stolen": 0,
                        "amount_used_while_supersonic": 193,
                        "time_zero_boost": 44.61,
                        "percent_zero_boost": 13.438367,
                        "time_full_boost": 26.86,
                        "percent_full_boost": 8.091336,
                        "time_boost_0_25": 134.85,
                        "time_boost_25_50": 64.49,
                        "time_boost_50_75": 62.33,
                        "time_boost_75_100": 74.8,
                        "percent_boost_0_25": 40.077873,
                        "percent_boost_25_50": 19.166643,
                        "percent_boost_50_75": 18.524685,
                        "percent_boost_75_100": 22.230812
                    },
                    "movement": {
                        "avg_speed": 1507,
                        "total_distance": 494362,
                        "time_supersonic_speed": 44.95,
                        "time_boost_speed": 120.87,
                        "time_slow_speed": 180.64,
                        "time_ground": 181.37,
                        "time_low_air": 132.64,
                        "time_high_air": 32.45,
                        "time_powerslide": 9.44,
                        "count_powerslide": 86,
                        "avg_powerslide_duration": 0.11,
                        "avg_speed_percentage": 65.521736,
                        "percent_slow_speed": 52.13877,
                        "percent_boost_speed": 34.887142,
                        "percent_supersonic_speed": 12.97408,
                        "percent_ground": 52.349476,
                        "percent_low_air": 38.28436,
                        "percent_high_air": 9.36616
                    },
                    "positioning": {
                        "avg_distance_to_ball": 2920,
                        "avg_distance_to_ball_possession": 3070,
                        "avg_distance_to_ball_no_possession": 2753,
                        "avg_distance_to_mates": 3893,
                        "time_defensive_third": 176.89,
                        "time_neutral_third": 110.01,
                        "time_offensive_third": 59.56,
                        "time_defensive_half": 240.84,
                        "time_offensive_half": 105.62,
                        "time_behind_ball": 268.19,
                        "time_infront_ball": 78.27,
                        "time_most_back": 120.6,
                        "time_most_forward": 98.2,
                        "time_closest_to_ball": 107.7,
                        "time_farthest_from_ball": 95.7,
                        "percent_defensive_third": 51.0564,
                        "percent_offensive_third": 17.19102,
                        "percent_neutral_third": 31.752584,
                        "percent_defensive_half": 69.51452,
                        "percent_offensive_half": 30.485483,
                        "percent_behind_ball": 77.408646,
                        "percent_infront_ball": 22.591352,
                        "percent_most_back": 36.329678,
                        "percent_most_forward": 29.581879,
                        "percent_closest_to_ball": 32.44367,
                        "percent_farthest_from_ball": 28.828775
                    },
                    "demo": {
                        "inflicted": 2,
                        "taken": 0
                    }
                }
            },
            {
                "start_time": 0,
                "end_time": 346.97595,
                "name": "KnightYuh :)",
                "id": {
                    "platform": "steam",
                    "id": "76561198999887273"
                },
                "car_id": 23,
                "car_name": "Octane",
                "camera": {
                    "fov": 110,
                    "height": 110,
                    "pitch": -4,
                    "distance": 270,
                    "stiffness": 0.4,
                    "swivel_speed": 7,
                    "transition_speed": 1.2
                },
                "steering_sensitivity": 1.77,
                "stats": {
                    "core": {
                        "shots": 2,
                        "shots_against": 4,
                        "goals": 0,
                        "goals_against": 0,
                        "saves": 2,
                        "assists": 1,
                        "score": 355,
                        "mvp": false,
                        "shooting_percentage": 0
                    },
                    "boost": {
                        "bpm": 454,
                        "bcpm": 488.55286,
                        "avg_amount": 42.82,
                        "amount_collected": 2703,
                        "amount_stolen": 616,
                        "amount_collected_big": 1870,
                        "amount_stolen_big": 420,
                        "amount_collected_small": 833,
                        "amount_stolen_small": 196,
                        "count_collected_big": 22,
                        "count_stolen_big": 5,
                        "count_collected_small": 69,
                        "count_stolen_small": 18,
                        "amount_overfill": 323,
                        "amount_overfill_stolen": 79,
                        "amount_used_while_supersonic": 428,
                        "time_zero_boost": 56.83,
                        "percent_zero_boost": 17.119534,
                        "time_full_boost": 24.52,
                        "percent_full_boost": 7.386432,
                        "time_boost_0_25": 146.67,
                        "time_boost_25_50": 64.89,
                        "time_boost_50_75": 46.69,
                        "time_boost_75_100": 74.73,
                        "percent_boost_0_25": 44.047688,
                        "percent_boost_25_50": 19.487656,
                        "percent_boost_50_75": 14.021863,
                        "percent_boost_75_100": 22.442791
                    },
                    "movement": {
                        "avg_speed": 1534,
                        "total_distance": 491155,
                        "time_supersonic_speed": 62.05,
                        "time_boost_speed": 122.09,
                        "time_slow_speed": 155.63,
                        "time_ground": 202.36,
                        "time_low_air": 113.34,
                        "time_high_air": 24.07,
                        "time_powerslide": 6.47,
                        "count_powerslide": 74,
                        "avg_powerslide_duration": 0.09,
                        "avg_speed_percentage": 66.695656,
                        "percent_slow_speed": 45.804516,
                        "percent_boost_speed": 35.933132,
                        "percent_supersonic_speed": 18.262354,
                        "percent_ground": 59.557934,
                        "percent_low_air": 33.357857,
                        "percent_high_air": 7.0842037
                    },
                    "positioning": {
                        "avg_distance_to_ball": 2968,
                        "avg_distance_to_ball_possession": 3300,
                        "avg_distance_to_ball_no_possession": 2552,
                        "avg_distance_to_mates": 3909,
                        "time_defensive_third": 155.69,
                        "time_neutral_third": 106.42,
                        "time_offensive_third": 77.65,
                        "time_defensive_half": 217.04,
                        "time_offensive_half": 122.73,
                        "time_behind_ball": 233.97,
                        "time_infront_ball": 105.8,
                        "time_most_back": 102.7,
                        "time_most_forward": 127.4,
                        "time_closest_to_ball": 95.5,
                        "time_farthest_from_ball": 123.8,
                        "percent_defensive_third": 45.82352,
                        "percent_offensive_third": 22.854366,
                        "percent_neutral_third": 31.32211,
                        "percent_defensive_half": 63.87851,
                        "percent_offensive_half": 36.121494,
                        "percent_behind_ball": 68.86128,
                        "percent_infront_ball": 31.13871,
                        "percent_most_back": 30.937464,
                        "percent_most_forward": 38.37812,
                        "percent_closest_to_ball": 28.768528,
                        "percent_farthest_from_ball": 37.29365
                    },
                    "demo": {
                        "inflicted": 3,
                        "taken": 2
                    }
                }
            }
        ],
        "stats": {
            "ball": {
                "possession_time": 146.65,
                "time_in_side": 167.97
            },
            "core": {
                "shots": 10,
                "shots_against": 4,
                "goals": 4,
                "goals_against": 0,
                "saves": 4,
                "assists": 2,
                "score": 1333,
                "shooting_percentage": 40
            },
            "boost": {
                "bpm": 1173,
                "bcpm": 1238.2817,
                "avg_amount": 132.57,
                "amount_collected": 6851,
                "amount_stolen": 1533,
                "amount_collected_big": 4752,
                "amount_stolen_big": 954,
                "amount_collected_small": 2099,
                "amount_stolen_small": 579,
                "count_collected_big": 59,
                "count_stolen_big": 11,
                "count_collected_small": 181,
                "count_stolen_small": 51,
                "amount_overfill": 1019,
                "amount_overfill_stolen": 92,
                "amount_used_while_supersonic": 865,
                "time_zero_boost": 133.8,
                "time_full_boost": 125.149994,
                "time_boost_0_25": 377.78998,
                "time_boost_25_50": 205.23,
                "time_boost_50_75": 182.89001,
                "time_boost_75_100": 237.40002
            },
            "movement": {
                "total_distance": 1532321,
                "time_supersonic_speed": 184.46,
                "time_boost_speed": 395.33,
                "time_slow_speed": 446.97,
                "time_ground": 524.82,
                "time_low_air": 417.25998,
                "time_high_air": 84.68,
                "time_powerslide": 20.269999,
                "count_powerslide": 198
            },
            "positioning": {
                "time_defensive_third": 496.90002,
                "time_neutral_third": 313.56,
                "time_offensive_third": 216.29001,
                "time_defensive_half": 677.57996,
                "time_offensive_half": 349.18002,
                "time_behind_ball": 764.64,
                "time_infront_ball": 262.12
            },
            "demo": {
                "inflicted": 7,
                "taken": 4
            }
        }
    },
    "orange": {
        "color": "orange",
        "players": [
            {
                "start_time": 0,
                "end_time": 346.97595,
                "name": "rapido",
                "id": {
                    "platform": "epic",
                    "id": "09d7567b88804249836a5f10bb2f03cc"
                },
                "car_id": 23,
                "car_name": "Octane",
                "camera": {
                    "fov": 109,
                    "height": 90,
                    "pitch": -4,
                    "distance": 270,
                    "stiffness": 0.45,
                    "swivel_speed": 7.4,
                    "transition_speed": 1.4
                },
                "steering_sensitivity": 2,
                "stats": {
                    "core": {
                        "shots": 0,
                        "shots_against": 10,
                        "goals": 0,
                        "goals_against": 4,
                        "saves": 3,
                        "assists": 0,
                        "score": 361,
                        "mvp": false,
                        "shooting_percentage": 0
                    },
                    "boost": {
                        "bpm": 434,
                        "bcpm": 472.10507,
                        "avg_amount": 50.45,
                        "amount_collected": 2612,
                        "amount_stolen": 860,
                        "amount_collected_big": 1947,
                        "amount_stolen_big": 466,
                        "amount_collected_small": 665,
                        "amount_stolen_small": 394,
                        "count_collected_big": 25,
                        "count_stolen_big": 6,
                        "count_collected_small": 53,
                        "count_stolen_small": 27,
                        "amount_overfill": 594,
                        "amount_overfill_stolen": 140,
                        "amount_used_while_supersonic": 683,
                        "time_zero_boost": 40.44,
                        "percent_zero_boost": 12.18219,
                        "time_full_boost": 55.36,
                        "percent_full_boost": 16.676708,
                        "time_boost_0_25": 130.52,
                        "time_boost_25_50": 51.42,
                        "time_boost_50_75": 53.27,
                        "time_boost_75_100": 104.74,
                        "percent_boost_0_25": 38.39388,
                        "percent_boost_25_50": 15.125753,
                        "percent_boost_50_75": 15.6699505,
                        "percent_boost_75_100": 30.810411
                    },
                    "movement": {
                        "avg_speed": 1707,
                        "total_distance": 558817,
                        "time_supersonic_speed": 87.44,
                        "time_boost_speed": 146.01,
                        "time_slow_speed": 112.97,
                        "time_ground": 179.59,
                        "time_low_air": 146.75,
                        "time_high_air": 20.09,
                        "time_powerslide": 6.43,
                        "count_powerslide": 54,
                        "avg_powerslide_duration": 0.12,
                        "avg_speed_percentage": 74.21739,
                        "percent_slow_speed": 32.610706,
                        "percent_boost_speed": 42.14826,
                        "percent_supersonic_speed": 25.241037,
                        "percent_ground": 51.8402,
                        "percent_low_air": 42.36065,
                        "percent_high_air": 5.7991514
                    },
                    "positioning": {
                        "avg_distance_to_ball": 2801,
                        "avg_distance_to_ball_possession": 2212,
                        "avg_distance_to_ball_no_possession": 3284,
                        "avg_distance_to_mates": 3840,
                        "time_defensive_third": 151.01,
                        "time_neutral_third": 94.37,
                        "time_offensive_third": 101.05,
                        "time_defensive_half": 198.61,
                        "time_offensive_half": 147.82,
                        "time_behind_ball": 216.83,
                        "time_infront_ball": 129.6,
                        "time_most_back": 96.2,
                        "time_most_forward": 129,
                        "goals_against_while_last_defender": 1,
                        "time_closest_to_ball": 106.8,
                        "time_farthest_from_ball": 105.1,
                        "percent_defensive_third": 43.590332,
                        "percent_offensive_third": 29.168953,
                        "percent_neutral_third": 27.240713,
                        "percent_defensive_half": 57.330486,
                        "percent_offensive_half": 42.669518,
                        "percent_behind_ball": 62.589848,
                        "percent_infront_ball": 37.41016,
                        "percent_most_back": 28.979395,
                        "percent_most_forward": 38.860104,
                        "percent_closest_to_ball": 32.17255,
                        "percent_farthest_from_ball": 31.660442
                    },
                    "demo": {
                        "inflicted": 2,
                        "taken": 1
                    }
                }
            },
            {
                "start_time": 0,
                "end_time": 346.97595,
                "name": "tcorrell",
                "id": {
                    "platform": "steam",
                    "id": "76561198241256564"
                },
                "car_id": 4284,
                "car_name": "Fennec",
                "camera": {
                    "fov": 110,
                    "height": 100,
                    "pitch": -3,
                    "distance": 270,
                    "stiffness": 0.35,
                    "swivel_speed": 7.3,
                    "transition_speed": 1.5
                },
                "steering_sensitivity": 1.5,
                "stats": {
                    "core": {
                        "shots": 2,
                        "shots_against": 10,
                        "goals": 0,
                        "goals_against": 4,
                        "saves": 3,
                        "assists": 0,
                        "score": 329,
                        "mvp": false,
                        "shooting_percentage": 0
                    },
                    "boost": {
                        "bpm": 397,
                        "bcpm": 384.62466,
                        "avg_amount": 46.94,
                        "amount_collected": 2128,
                        "amount_stolen": 455,
                        "amount_collected_big": 1281,
                        "amount_stolen_big": 155,
                        "amount_collected_small": 847,
                        "amount_stolen_small": 300,
                        "count_collected_big": 19,
                        "count_stolen_big": 3,
                        "count_collected_small": 79,
                        "count_stolen_small": 28,
                        "amount_overfill": 642,
                        "amount_overfill_stolen": 151,
                        "amount_used_while_supersonic": 478,
                        "time_zero_boost": 34.43,
                        "percent_zero_boost": 10.371732,
                        "time_full_boost": 26.67,
                        "percent_full_boost": 8.034101,
                        "time_boost_0_25": 134.74,
                        "time_boost_25_50": 60.17,
                        "time_boost_50_75": 55.9,
                        "time_boost_75_100": 83.11,
                        "percent_boost_0_25": 40.350986,
                        "percent_boost_25_50": 18.019287,
                        "percent_boost_50_75": 16.740538,
                        "percent_boost_75_100": 24.889196
                    },
                    "movement": {
                        "avg_speed": 1600,
                        "total_distance": 519602,
                        "time_supersonic_speed": 84.51,
                        "time_boost_speed": 106.97,
                        "time_slow_speed": 151.97,
                        "time_ground": 164.33,
                        "time_low_air": 158.29,
                        "time_high_air": 20.83,
                        "time_powerslide": 8.88,
                        "count_powerslide": 72,
                        "avg_powerslide_duration": 0.12,
                        "avg_speed_percentage": 69.565216,
                        "percent_slow_speed": 44.24807,
                        "percent_boost_speed": 31.145725,
                        "percent_supersonic_speed": 24.606201,
                        "percent_ground": 47.84685,
                        "percent_low_air": 46.088223,
                        "percent_high_air": 6.0649295
                    },
                    "positioning": {
                        "avg_distance_to_ball": 2810,
                        "avg_distance_to_ball_possession": 2704,
                        "avg_distance_to_ball_no_possession": 2904,
                        "avg_distance_to_mates": 3686,
                        "time_defensive_third": 168.74,
                        "time_neutral_third": 96.72,
                        "time_offensive_third": 77.99,
                        "time_defensive_half": 211.87,
                        "time_offensive_half": 131.58,
                        "time_behind_ball": 254.65,
                        "time_infront_ball": 88.8,
                        "time_most_back": 124.8,
                        "time_most_forward": 94.2,
                        "goals_against_while_last_defender": 1,
                        "time_closest_to_ball": 120.2,
                        "time_farthest_from_ball": 105.7,
                        "percent_defensive_third": 49.130875,
                        "percent_offensive_third": 22.707817,
                        "percent_neutral_third": 28.161303,
                        "percent_defensive_half": 61.688744,
                        "percent_offensive_half": 38.311253,
                        "percent_behind_ball": 74.14471,
                        "percent_infront_ball": 25.855291,
                        "percent_most_back": 37.59489,
                        "percent_most_forward": 28.376913,
                        "percent_closest_to_ball": 36.209183,
                        "percent_farthest_from_ball": 31.841187
                    },
                    "demo": {
                        "inflicted": 0,
                        "taken": 1
                    }
                }
            },
            {
                "start_time": 0,
                "end_time": 346.97595,
                "name": "jerbear0",
                "id": {
                    "platform": "epic",
                    "id": "03c13eea03c14876a7f0c9dd7cd75d0d"
                },
                "car_id": 4284,
                "car_name": "Fennec",
                "camera": {
                    "fov": 110,
                    "height": 90,
                    "pitch": -4,
                    "distance": 270,
                    "stiffness": 0.35,
                    "swivel_speed": 6.9,
                    "transition_speed": 1.6
                },
                "steering_sensitivity": 1.5,
                "stats": {
                    "core": {
                        "shots": 2,
                        "shots_against": 10,
                        "goals": 0,
                        "goals_against": 4,
                        "saves": 0,
                        "assists": 0,
                        "score": 188,
                        "mvp": false,
                        "shooting_percentage": 0
                    },
                    "boost": {
                        "bpm": 373,
                        "bcpm": 402.87988,
                        "avg_amount": 47.77,
                        "amount_collected": 2229,
                        "amount_stolen": 615,
                        "amount_collected_big": 1497,
                        "amount_stolen_big": 390,
                        "amount_collected_small": 732,
                        "amount_stolen_small": 225,
                        "count_collected_big": 19,
                        "count_stolen_big": 4,
                        "count_collected_small": 68,
                        "count_stolen_small": 20,
                        "amount_overfill": 363,
                        "amount_overfill_stolen": 22,
                        "amount_used_while_supersonic": 279,
                        "time_zero_boost": 33.72,
                        "percent_zero_boost": 10.15785,
                        "time_full_boost": 45.29,
                        "percent_full_boost": 13.64321,
                        "time_boost_0_25": 102.07,
                        "time_boost_25_50": 74.07,
                        "time_boost_50_75": 45.21,
                        "time_boost_75_100": 98.59,
                        "percent_boost_0_25": 31.902857,
                        "percent_boost_25_50": 23.151217,
                        "percent_boost_50_75": 14.1307745,
                        "percent_boost_75_100": 30.815153
                    },
                    "movement": {
                        "avg_speed": 1608,
                        "total_distance": 508133,
                        "time_supersonic_speed": 47.99,
                        "time_boost_speed": 150.58,
                        "time_slow_speed": 135.34,
                        "time_ground": 205.19,
                        "time_low_air": 104.39,
                        "time_high_air": 24.32,
                        "time_powerslide": 5.7,
                        "count_powerslide": 59,
                        "avg_powerslide_duration": 0.1,
                        "avg_speed_percentage": 69.91304,
                        "percent_slow_speed": 40.531883,
                        "percent_boost_speed": 45.09599,
                        "percent_supersonic_speed": 14.372137,
                        "percent_ground": 61.452526,
                        "percent_low_air": 31.26385,
                        "percent_high_air": 7.2836175
                    },
                    "positioning": {
                        "avg_distance_to_ball": 2952,
                        "avg_distance_to_ball_possession": 2602,
                        "avg_distance_to_ball_no_possession": 3202,
                        "avg_distance_to_mates": 3812,
                        "time_defensive_third": 157.2,
                        "time_neutral_third": 94.64,
                        "time_offensive_third": 82.07,
                        "time_defensive_half": 206.96,
                        "time_offensive_half": 126.94,
                        "time_behind_ball": 229.42,
                        "time_infront_ball": 104.48,
                        "time_most_back": 120.6,
                        "time_most_forward": 106.2,
                        "goals_against_while_last_defender": 2,
                        "time_closest_to_ball": 102.4,
                        "time_farthest_from_ball": 131,
                        "percent_defensive_third": 47.078556,
                        "percent_offensive_third": 24.578482,
                        "percent_neutral_third": 28.34297,
                        "percent_defensive_half": 61.982624,
                        "percent_offensive_half": 38.01737,
                        "percent_behind_ball": 68.7092,
                        "percent_infront_ball": 31.290806,
                        "percent_most_back": 36.329678,
                        "percent_most_forward": 31.991808,
                        "percent_closest_to_ball": 30.847092,
                        "percent_farthest_from_ball": 39.462585
                    },
                    "demo": {
                        "inflicted": 2,
                        "taken": 5
                    }
                }
            }
        ],
        "stats": {
            "ball": {
                "possession_time": 145.45,
                "time_in_side": 158.39
            },
            "core": {
                "shots": 4,
                "shots_against": 10,
                "goals": 0,
                "goals_against": 4,
                "saves": 6,
                "assists": 0,
                "score": 878,
                "shooting_percentage": 0
            },
            "boost": {
                "bpm": 1204,
                "bcpm": 1259.6096,
                "avg_amount": 145.16,
                "amount_collected": 6969,
                "amount_stolen": 1930,
                "amount_collected_big": 4725,
                "amount_stolen_big": 1011,
                "amount_collected_small": 2244,
                "amount_stolen_small": 919,
                "count_collected_big": 63,
                "count_stolen_big": 13,
                "count_collected_small": 200,
                "count_stolen_small": 75,
                "amount_overfill": 1599,
                "amount_overfill_stolen": 313,
                "amount_used_while_supersonic": 1440,
                "time_zero_boost": 108.59,
                "time_full_boost": 127.32,
                "time_boost_0_25": 367.33002,
                "time_boost_25_50": 185.66,
                "time_boost_50_75": 154.38,
                "time_boost_75_100": 286.44
            },
            "movement": {
                "total_distance": 1586552,
                "time_supersonic_speed": 219.94002,
                "time_boost_speed": 403.56,
                "time_slow_speed": 400.28,
                "time_ground": 549.11,
                "time_low_air": 409.43,
                "time_high_air": 65.24,
                "time_powerslide": 21.009998,
                "count_powerslide": 185
            },
            "positioning": {
                "time_defensive_third": 476.95,
                "time_neutral_third": 285.72998,
                "time_offensive_third": 261.11002,
                "time_defensive_half": 617.44,
                "time_offensive_half": 406.34003,
                "time_behind_ball": 700.89996,
                "time_infront_ball": 322.88
            },
            "demo": {
                "inflicted": 4,
                "taken": 7
            }
        }
    },
    "playlist_name": "Private",
    "map_name": "Mannfield (Dusk)",
    "server": {
        "name": "USE1-02CFC3BF7353B3A64-Aurora12",
        "region": "USE"
    }
}