{
    "id": "af37f018-ac07-472a-8e6a-ec41734d1585",
    "link": "https://ballchasing.com/api/replays/af37f018-ac07-472a-8e6a-ec41734d1585",
    "created": "2024-04-11T16:59:45.617888Z",
    "uploader": {
        "steam_id": "76561198342081613",
        "name": "Waldi (chat off)",
        "profile_url": "https://steamcommunity.com/id/dgswaldi/",
        "avatar": "https://avatars.steamstatic.com/38307a70ccfc1c9fd9f3c7019b5d97d91f1c9e9a.jpg"
    },
    "status": "ok",
    "rocket_league_id": "17BBCDFB4B709BE8B4F858B16690E003",
    "match_guid": "2914062811EEF8249A1F5DA2066AC2C0",
    "title": "2024-04-11.18.59 Waldi Ranked Doubles Loss",
    "map_code": "eurostadium_rainy_p",
    "match_type": "Online",
    "team_size": 2,
    "playlist_id": "ranked-doubles",
    "duration": 288,
    "overtime": false,
    "season": 14,
    "season_type": "free2play",
    "date": "2024-04-11T18:59:48+02:00",
    "date_has_timezone": true,
    "visibility": "public",
    "min_rank": {
        "id": "grand-champion-1",
        "tier": 19,
        "division": 3,
        "name": "Grand Champion I Division 3"
    },
    "max_rank": {
        "id": "grand-champion-1",
        "tier": 19,
        "division": 3,
        "name": "Grand Champion I Division 3"
    },
    "blue": {
        "color": "blue",
        "players": [
            {
                "start_time": 0,
                "end_time": 288.49496,
                "name": "Bassem is back",
                "id": {
                    "platform": "epic",
                    "id": "5a09e24f6c7f4351829227c9dde2482b"
                },
                "mvp": true,
                "car_id": 4284,
                "car_name": "Fennec",
                "camera": {
                    "fov": 110,
                    "height": 110,
                    "pitch": -3,
                    "distance": 280,
                    "stiffness": 0.35,
                    "swivel_speed": 4.9,
                    "transition_speed": 1.4
                },
                "steering_sensitivity": 1.85,
                "stats": {
                    "core": {
                        "shots": 4,
                        "shots_against": 7,
                        "goals": 2,
                        "goals_against": 0,
                        "saves": 3,
                        "assists": 1,
                        "score": 566,
                        "mvp": true,
                        "shooting_percentage": 50
                    },
                    "boost": {
                        "bpm": 337,
                        "bcpm": 345.26907,
                        "avg_amount": 45.62,
                        "amount_collected": 1591,
                        "amount_stolen": 207,
                        "amount_collected_big": 1092,
                        "amount_stolen_big": 100,
                        "amount_collected_small": 499,
                        "amount_stolen_small": 107,
                        "count_collected_big": 14,
                        "count_stolen_big": 1,
                        "count_collected_small": 44,
                        "count_stolen_small": 9,
                        "amount_overfill": 232,
                        "amount_overfill_stolen": 0,
                        "amount_used_while_supersonic": 229,
                        "time_zero_boost": 35.33,
                        "percent_zero_boost": 12.7785015,
                        "time_full_boost": 33.37,
                        "percent_full_boost": 12.069589,
                        "time_boost_0_25": 104.69,
                        "time_boost_25_50": 52.96,
                        "time_boost_50_75": 59.92,
                        "time_boost_75_100": 63.54,
                        "percent_boost_0_25": 37.24165,
                        "percent_boost_25_50": 18.839602,
                        "percent_boost_50_75": 21.3155,
                        "percent_boost_75_100": 22.603252
                    },
                    "movement": {
                        "avg_speed": 1441,
                        "total_distance": 391672,
                        "time_supersonic_speed": 29.39,
                        "time_boost_speed": 110.58,
                        "time_slow_speed": 148.24,
                        "time_ground": 166.17,
                        "time_low_air": 104.87,
                        "time_high_air": 17.17,
                        "time_powerslide": 8.54,
                        "count_powerslide": 59,
                        "avg_powerslide_duration": 0.14,
                        "avg_speed_percentage": 62.652172,
                        "percent_slow_speed": 51.43472,
                        "percent_boost_speed": 38.367855,
                        "percent_supersonic_speed": 10.197425,
                        "percent_ground": 57.655872,
                        "percent_low_air": 36.38666,
                        "percent_high_air": 5.9574614
                    },
                    "positioning": {
                        "avg_distance_to_ball": 2352,
                        "avg_distance_to_ball_possession": 2360,
                        "avg_distance_to_ball_no_possession": 2333,
                        "avg_distance_to_mates": 3004,
                        "time_defensive_third": 148.54,
                        "time_neutral_third": 112.15,
                        "time_offensive_third": 27.52,
                        "time_defensive_half": 202.62,
                        "time_offensive_half": 85.59,
                        "time_behind_ball": 256.2,
                        "time_infront_ball": 32.01,
                        "time_most_back": 156.2,
                        "time_most_forward": 119,
                        "time_closest_to_ball": 143.4,
                        "time_farthest_from_ball": 131.8,
                        "percent_defensive_third": 51.538807,
                        "percent_offensive_third": 9.5485935,
                        "percent_neutral_third": 38.9126,
                        "percent_defensive_half": 70.30291,
                        "percent_offensive_half": 29.697096,
                        "percent_behind_ball": 88.89352,
                        "percent_infront_ball": 11.106483,
                        "percent_most_back": 56.495945,
                        "percent_most_forward": 43.04109,
                        "percent_closest_to_ball": 51.866314,
                        "percent_farthest_from_ball": 47.670715
                    },
                    "demo": {
                        "inflicted": 2,
                        "taken": 0
                    }
                }
            },
            {
                "start_time": 0,
                "end_time": 288.49496,
                "name": "Atom-Raizen",
                "id": {
                    "platform": "epic",
                    "id": "7476e94eebf641f8a6565fa5523f0382"
                },
                "car_id": 4284,
                "car_name": "Fennec",
                "camera": {
                    "fov": 110,
                    "height": 110,
                    "pitch": -3,
                    "distance": 270,
                    "stiffness": 0.4,
                    "swivel_speed": 4.8,
                    "transition_speed": 1.5
                },
                "steering_sensitivity": 1.4,
                "stats": {
                    "core": {
                        "shots": 2,
                        "shots_against": 7,
                        "goals": 2,
                        "goals_against": 0,
                        "saves": 1,
                        "assists": 1,
                        "score": 480,
                        "mvp": false,
                        "shooting_percentage": 100
                    },
                    "boost": {
                        "bpm": 388,
                        "bcpm": 412.5434,
                        "avg_amount": 47.56,
                        "amount_collected": 1901,
                        "amount_stolen": 102,
                        "amount_collected_big": 1356,
                        "amount_stolen_big": 0,
                        "amount_collected_small": 545,
                        "amount_stolen_small": 102,
                        "count_collected_big": 15,
                        "count_stolen_big": 0,
                        "count_collected_small": 50,
                        "count_stolen_small": 9,
                        "amount_overfill": 154,
                        "amount_overfill_stolen": 0,
                        "amount_used_while_supersonic": 232,
                        "time_zero_boost": 55.11,
                        "percent_zero_boost": 19.932724,
                        "time_full_boost": 34.39,
                        "percent_full_boost": 12.438512,
                        "time_boost_0_25": 104.27,
                        "time_boost_25_50": 63.2,
                        "time_boost_50_75": 45.77,
                        "time_boost_75_100": 73.42,
                        "percent_boost_0_25": 36.3741,
                        "percent_boost_25_50": 22.047024,
                        "percent_boost_50_75": 15.96665,
                        "percent_boost_75_100": 25.612223
                    },
                    "movement": {
                        "avg_speed": 1521,
                        "total_distance": 416047,
                        "time_supersonic_speed": 53.11,
                        "time_boost_speed": 97.66,
                        "time_slow_speed": 137.41,
                        "time_ground": 169.25,
                        "time_low_air": 107.87,
                        "time_high_air": 11.06,
                        "time_powerslide": 5.52,
                        "count_powerslide": 38,
                        "avg_powerslide_duration": 0.15,
                        "avg_speed_percentage": 66.13043,
                        "percent_slow_speed": 47.682007,
                        "percent_boost_speed": 33.888542,
                        "percent_supersonic_speed": 18.429455,
                        "percent_ground": 58.730656,
                        "percent_low_air": 37.43147,
                        "percent_high_air": 3.8378792
                    },
                    "positioning": {
                        "avg_distance_to_ball": 2564,
                        "avg_distance_to_ball_possession": 2492,
                        "avg_distance_to_ball_no_possession": 2656,
                        "avg_distance_to_mates": 3004,
                        "time_defensive_third": 141.55,
                        "time_neutral_third": 109.66,
                        "time_offensive_third": 36.96,
                        "time_defensive_half": 197.37,
                        "time_offensive_half": 90.81,
                        "time_behind_ball": 217.55,
                        "time_infront_ball": 70.63,
                        "time_most_back": 119.7,
                        "time_most_forward": 156,
                        "time_closest_to_ball": 131.6,
                        "time_farthest_from_ball": 144.1,
                        "percent_defensive_third": 49.120308,
                        "percent_offensive_third": 12.825762,
                        "percent_neutral_third": 38.053925,
                        "percent_defensive_half": 68.48845,
                        "percent_offensive_half": 31.511557,
                        "percent_behind_ball": 75.49101,
                        "percent_infront_ball": 24.508986,
                        "percent_most_back": 43.29427,
                        "percent_most_forward": 56.42361,
                        "percent_closest_to_ball": 47.59838,
                        "percent_farthest_from_ball": 52.119503
                    },
                    "demo": {
                        "inflicted": 3,
                        "taken": 0
                    }
                }
            }
        ],
        "stats": {
            "ball": {
                "possession_time": 127.68,
                "time_in_side": 129.62
            },
            "core": {
                "shots": 6,
                "shots_against": 7,
                "goals": 4,
                "goals_against": 0,
                "saves": 4,
                "assists": 2,
                "score": 1046,
                "shooting_percentage": 66.666664
            },
            "boost": {
                "bpm": 725,
                "bcpm": 757.8125,
                "avg_amount": 93.18,
                "amount_collected": 3492,
                "amount_stolen": 309,
                "amount_collected_big": 2448,
                "amount_stolen_big": 100,
                "amount_collected_small": 1044,
                "amount_stolen_small": 209,
                "count_collected_big": 29,
                "count_stolen_big": 1,
                "count_collected_small": 94,
                "count_stolen_small": 18,
                "amount_overfill": 386,
                "amount_overfill_stolen": 0,
                "amount_used_while_supersonic": 461,
                "time_zero_boost": 90.44,
                "time_full_boost": 67.759995,
                "time_boost_0_25": 208.95999,
                "time_boost_25_50": 116.16,
                "time_boost_50_75": 105.69,
                "time_boost_75_100": 136.95999
            },
            "movement": {
                "total_distance": 807719,
                "time_supersonic_speed": 82.5,
                "time_boost_speed": 208.24,
                "time_slow_speed": 285.65002,
                "time_ground": 335.41998,
                "time_low_air": 212.74,
                "time_high_air": 28.23,
                "time_powerslide": 14.059999,
                "count_powerslide": 97
            },
            "positioning": {
                "time_defensive_third": 290.09,
                "time_neutral_third": 221.81,
                "time_offensive_third": 64.479996,
                "time_defensive_half": 399.99,
                "time_offensive_half": 176.4,
                "time_behind_ball": 473.75,
                "time_infront_ball": 102.64
            },
            "demo": {
                "inflicted": 5,
                "taken": 0
            }
        }
    },
    "orange": {
        "color": "orange",
        "players": [
            {
                "start_time": 0,
                "end_time": 288.49496,
                "name": "Waldi",
                "id": {
                    "platform": "steam",
                    "id": "76561198342081613"
                },
                "rank": {
                    "id": "grand-champion-1",
                    "tier": 19,
                    "division": 3,
                    "name": "Grand Champion I Division 3"
                },
                "car_id": 2269,
                "car_name": "Fast & Furious Nissan Skyline",
                "camera": {
                    "fov": 110,
                    "height": 130,
                    "pitch": -5,
                    "distance": 290,
                    "stiffness": 0.6,
                    "swivel_speed": 4.4,
                    "transition_speed": 1
                },
                "steering_sensitivity": 1.92,
                "stats": {
                    "core": {
                        "shots": 3,
                        "shots_against": 6,
                        "goals": 0,
                        "goals_against": 4,
                        "saves": 1,
                        "assists": 0,
                        "score": 195,
                        "mvp": false,
                        "shooting_percentage": 0
                    },
                    "boost": {
                        "bpm": 491,
                        "bcpm": 490.01733,
                        "avg_amount": 45.62,
                        "amount_collected": 2258,
                        "amount_stolen": 587,
                        "amount_collected_big": 1630,
                        "amount_stolen_big": 325,
                        "amount_collected_small": 628,
                        "amount_stolen_small": 262,
                        "count_collected_big": 22,
                        "count_stolen_big": 4,
                        "count_collected_small": 56,
                        "count_stolen_small": 23,
                        "amount_overfill": 288,
                        "amount_overfill_stolen": 78,
                        "amount_used_while_supersonic": 367,
                        "time_zero_boost": 17.37,
                        "percent_zero_boost": 6.2825522,
                        "time_full_boost": 23.75,
                        "percent_full_boost": 8.590133,
                        "time_boost_0_25": 90.72,
                        "time_boost_25_50": 63.71,
                        "time_boost_50_75": 60.02,
                        "time_boost_75_100": 54.51,
                        "percent_boost_0_25": 33.729923,
                        "percent_boost_25_50": 23.687538,
                        "percent_boost_50_75": 22.315586,
                        "percent_boost_75_100": 20.266954
                    },
                    "movement": {
                        "avg_speed": 1616,
                        "total_distance": 428082,
                        "time_supersonic_speed": 44.48,
                        "time_boost_speed": 129.24,
                        "time_slow_speed": 105.35,
                        "time_ground": 154.24,
                        "time_low_air": 110.42,
                        "time_high_air": 14.41,
                        "time_powerslide": 7.57,
                        "count_powerslide": 52,
                        "avg_powerslide_duration": 0.15,
                        "avg_speed_percentage": 70.26087,
                        "percent_slow_speed": 37.750385,
                        "percent_boost_speed": 46.310963,
                        "percent_supersonic_speed": 15.938653,
                        "percent_ground": 55.26929,
                        "percent_low_air": 39.56713,
                        "percent_high_air": 5.163579
                    },
                    "positioning": {
                        "avg_distance_to_ball": 2271,
                        "avg_distance_to_ball_possession": 2099,
                        "avg_distance_to_ball_no_possession": 2412,
                        "avg_distance_to_mates": 3360,
                        "time_defensive_third": 114.27,
                        "time_neutral_third": 106.92,
                        "time_offensive_third": 57.89,
                        "time_defensive_half": 167.03,
                        "time_offensive_half": 112.04,
                        "time_behind_ball": 210.87,
                        "time_infront_ball": 68.2,
                        "time_most_back": 143.9,
                        "time_most_forward": 136,
                        "goals_against_while_last_defender": 4,
                        "time_closest_to_ball": 160.3,
                        "time_farthest_from_ball": 119.6,
                        "percent_defensive_third": 40.945248,
                        "percent_offensive_third": 20.743155,
                        "percent_neutral_third": 38.311592,
                        "percent_defensive_half": 59.852364,
                        "percent_offensive_half": 40.147633,
                        "percent_behind_ball": 75.56168,
                        "percent_infront_ball": 24.43831,
                        "percent_most_back": 52.047157,
                        "percent_most_forward": 49.18981,
                        "percent_closest_to_ball": 57.978874,
                        "percent_farthest_from_ball": 43.2581
                    },
                    "demo": {
                        "inflicted": 0,
                        "taken": 3
                    }
                }
            },
            {
                "start_time": 0,
                "end_time": 288.49496,
                "name": "poow",
                "id": {
                    "platform": "steam",
                    "id": "76561198361382705"
                },
                "car_id": 23,
                "car_name": "Octane",
                "camera": {
                    "fov": 110,
                    "height": 110,
                    "pitch": -4,
                    "distance": 270,
                    "stiffness": 0.45,
                    "swivel_speed": 6,
                    "transition_speed": 1.4
                },
                "steering_sensitivity": 1.3,
                "stats": {
                    "core": {
                        "shots": 4,
                        "shots_against": 6,
                        "goals": 0,
                        "goals_against": 4,
                        "saves": 1,
                        "assists": 0,
                        "score": 164,
                        "mvp": false,
                        "shooting_percentage": 0
                    },
                    "boost": {
                        "bpm": 389,
                        "bcpm": 403.86282,
                        "avg_amount": 53.83,
                        "amount_collected": 1861,
                        "amount_stolen": 621,
                        "amount_collected_big": 1343,
                        "amount_stolen_big": 419,
                        "amount_collected_small": 518,
                        "amount_stolen_small": 202,
                        "count_collected_big": 16,
                        "count_stolen_big": 5,
                        "count_collected_small": 46,
                        "count_stolen_small": 18,
                        "amount_overfill": 274,
                        "amount_overfill_stolen": 91,
                        "amount_used_while_supersonic": 310,
                        "time_zero_boost": 13.82,
                        "percent_zero_boost": 4.9985533,
                        "time_full_boost": 47.54,
                        "percent_full_boost": 17.194733,
                        "time_boost_0_25": 64.13,
                        "time_boost_25_50": 56.32,
                        "time_boost_50_75": 74.54,
                        "time_boost_75_100": 77.96,
                        "percent_boost_0_25": 23.495146,
                        "percent_boost_25_50": 20.633818,
                        "percent_boost_50_75": 27.309032,
                        "percent_boost_75_100": 28.56201
                    },
                    "movement": {
                        "avg_speed": 1622,
                        "total_distance": 432914,
                        "time_supersonic_speed": 60.41,
                        "time_boost_speed": 102.39,
                        "time_slow_speed": 119.36,
                        "time_ground": 170.62,
                        "time_low_air": 102.96,
                        "time_high_air": 8.58,
                        "time_powerslide": 4.34,
                        "count_powerslide": 31,
                        "avg_powerslide_duration": 0.14,
                        "avg_speed_percentage": 70.521736,
                        "percent_slow_speed": 42.30224,
                        "percent_boost_speed": 36.28792,
                        "percent_supersonic_speed": 21.409838,
                        "percent_ground": 60.469242,
                        "percent_low_air": 36.489937,
                        "percent_high_air": 3.0408282
                    },
                    "positioning": {
                        "avg_distance_to_ball": 2911,
                        "avg_distance_to_ball_possession": 2518,
                        "avg_distance_to_ball_no_possession": 3196,
                        "avg_distance_to_mates": 3360,
                        "time_defensive_third": 119.54,
                        "time_neutral_third": 96.3,
                        "time_offensive_third": 66.32,
                        "time_defensive_half": 171.36,
                        "time_offensive_half": 110.8,
                        "time_behind_ball": 200.81,
                        "time_infront_ball": 81.36,
                        "time_most_back": 145.2,
                        "time_most_forward": 138.6,
                        "time_closest_to_ball": 117.5,
                        "time_farthest_from_ball": 166.3,
                        "percent_defensive_third": 42.36603,
                        "percent_offensive_third": 23.504395,
                        "percent_neutral_third": 34.12957,
                        "percent_defensive_half": 60.7315,
                        "percent_offensive_half": 39.2685,
                        "percent_behind_ball": 71.16632,
                        "percent_infront_ball": 28.833683,
                        "percent_most_back": 52.51736,
                        "percent_most_forward": 50.13021,
                        "percent_closest_to_ball": 42.49855,
                        "percent_farthest_from_ball": 60.149014
                    },
                    "demo": {
                        "inflicted": 0,
                        "taken": 2
                    }
                }
            }
        ],
        "stats": {
            "ball": {
                "possession_time": 115.84,
                "time_in_side": 141.55
            },
            "core": {
                "shots": 7,
                "shots_against": 6,
                "goals": 0,
                "goals_against": 4,
                "saves": 2,
                "assists": 0,
                "score": 359,
                "shooting_percentage": 0
            },
            "boost": {
                "bpm": 880,
                "bcpm": 893.8801,
                "avg_amount": 99.45,
                "amount_collected": 4119,
                "amount_stolen": 1208,
                "amount_collected_big": 2973,
                "amount_stolen_big": 744,
                "amount_collected_small": 1146,
                "amount_stolen_small": 464,
                "count_collected_big": 38,
                "count_stolen_big": 9,
                "count_collected_small": 102,
                "count_stolen_small": 41,
                "amount_overfill": 562,
                "amount_overfill_stolen": 169,
                "amount_used_while_supersonic": 677,
                "time_zero_boost": 31.19,
                "time_full_boost": 71.29,
                "time_boost_0_25": 154.85,
                "time_boost_25_50": 120.03,
                "time_boost_50_75": 134.56,
                "time_boost_75_100": 132.47
            },
            "movement": {
                "total_distance": 860996,
                "time_supersonic_speed": 104.89,
                "time_boost_speed": 231.63,
                "time_slow_speed": 224.70999,
                "time_ground": 324.86,
                "time_low_air": 213.38,
                "time_high_air": 22.99,
                "time_powerslide": 11.91,
                "count_powerslide": 83
            },
            "positioning": {
                "time_defensive_third": 233.81,
                "time_neutral_third": 203.22,
                "time_offensive_third": 124.21,
                "time_defensive_half": 338.39,
                "time_offensive_half": 222.84,
                "time_behind_ball": 411.68,
                "time_infront_ball": 149.56
            },
            "demo": {
                "inflicted": 0,
                "taken": 5
            }
        }
    },
    "playlist_name": "Ranked Doubles",
    "map_name": "Mannfield (Stormy)",
    "server": {
        "name": "EU-1641901-14478238",
        "region": "EU"
    }
}