{
    "id": "13c0200f-e304-4a0a-b97a-4d1174c6ab45",
    "link": "https://ballchasing.com/api/replays/13c0200f-e304-4a0a-b97a-4d1174c6ab45",
    "created": "2025-02-02T12:57:16.608424Z",
    "uploader": {
        "steam_id": "76561198406569848",
        "name": "Tr3bla",
        "profile_url": "https://steamcommunity.com/id/Tr3bla/",
        "avatar": "https://avatars.steamstatic.com/3810a16c546e69b8919a2715f5747c3f41a66640.jpg"
    },
    "status": "ok",
    "rocket_league_id": "3F9C096E44EC59694BA23FA64A2F7954",
    "match_guid": "111DFBEE11EFE164E993EE93E1517F09",
    "title": "2025-02-02.13.57 Tr3bla Ranked Doubles Loss",
    "map_code": "stadium_foggy_p",
    "match_type": "Online",
    "team_size": 2,
    "playlist_id": "ranked-doubles",
    "duration": 457,
    "overtime": true,
    "overtime_seconds": 86,
    "season": 17,
    "season_type": "free2play",
    "date": "2025-02-02T13:57:14+01:00",
    "date_has_timezone": true,
    "visibility": "public",
    "min_rank": {
        "id": "supersonic-legend",
        "tier": 22,
        "name": "Supersonic Legend"
    },
    "max_rank": {
        "id": "supersonic-legend",
        "tier": 22,
        "name": "Supersonic Legend"
    },
    "groups": [
        {
            "id": "supersonic-legend-2s-replays-202-v1o8n3flw0",
            "name": "Supersonic Legend 2s Replays (2024-12-01) Part 43",
            "link": "https://ballchasing.com/api/groups/supersonic-legend-2s-replays-202-v1o8n3flw0"
        }
    ],
    "blue": {
        "color": "blue",
        "players": [
            {
                "start_time": 0,
                "end_time": 457.87103,
                "name": "Rox",
                "id": {
                    "platform": "steam",
                    "id": "76561198273335578"
                },
                "mvp": true,
                "rank": {
                    "id": "supersonic-legend",
                    "tier": 22,
                    "name": "Supersonic Legend"
                },
                "car_id": 4284,
                "car_name": "Fennec",
                "camera": {
                    "fov": 110,
                    "height": 100,
                    "pitch": -3,
                    "distance": 270,
                    "stiffness": 0.4,
                    "swivel_speed": 4.7,
                    "transition_speed": 1.2
                },
                "steering_sensitivity": 1.3,
                "stats": {
                    "core": {
                        "shots": 9,
                        "shots_against": 9,
                        "goals": 4,
                        "goals_against": 3,
                        "saves": 2,
                        "assists": 0,
                        "score": 1013,
                        "mvp": true,
                        "shooting_percentage": 44.444443
                    },
                    "boost": {
                        "bpm": 492,
                        "bcpm": 466.72968,
                        "avg_amount": 48.32,
                        "amount_collected": 3375,
                        "amount_stolen": 533,
                        "amount_collected_big": 2400,
                        "amount_stolen_big": 304,
                        "amount_collected_small": 975,
                        "amount_stolen_small": 229,
                        "count_collected_big": 29,
                        "count_stolen_big": 4,
                        "count_collected_small": 88,
                        "count_stolen_small": 22,
                        "amount_overfill": 512,
                        "amount_overfill_stolen": 95,
                        "amount_used_while_supersonic": 789,
                        "time_zero_boost": 54.6,
                        "percent_zero_boost": 12.5844145,
                        "time_full_boost": 50.82,
                        "percent_full_boost": 11.713186,
                        "time_boost_0_25": 151.3,
                        "time_boost_25_50": 108.46,
                        "time_boost_50_75": 79.96,
                        "time_boost_75_100": 98.61,
                        "percent_boost_0_25": 34.517372,
                        "percent_boost_25_50": 24.743914,
                        "percent_boost_50_75": 18.241962,
                        "percent_boost_75_100": 22.496748
                    },
                    "movement": {
                        "avg_speed": 1595,
                        "total_distance": 679987,
                        "time_supersonic_speed": 81.9,
                        "time_boost_speed": 191.89,
                        "time_slow_speed": 183.39,
                        "time_ground": 279.84,
                        "time_low_air": 150.39,
                        "time_high_air": 26.96,
                        "time_powerslide": 7.66,
                        "count_powerslide": 58,
                        "avg_powerslide_duration": 0.13,
                        "avg_speed_percentage": 69.347824,
                        "percent_slow_speed": 40.113304,
                        "percent_boost_speed": 41.972527,
                        "percent_supersonic_speed": 17.91417,
                        "percent_ground": 61.20869,
                        "percent_low_air": 32.89442,
                        "percent_high_air": 5.896892
                    },
                    "positioning": {
                        "avg_distance_to_ball": 2344,
                        "avg_distance_to_ball_possession": 2193,
                        "avg_distance_to_ball_no_possession": 2445,
                        "avg_distance_to_mates": 3034,
                        "time_defensive_third": 230.08,
                        "time_neutral_third": 142.01,
                        "time_offensive_third": 85.1,
                        "time_defensive_half": 308.76,
                        "time_offensive_half": 148.42,
                        "time_behind_ball": 374.28,
                        "time_infront_ball": 82.9,
                        "time_most_back": 219.4,
                        "time_most_forward": 215.2,
                        "goals_against_while_last_defender": 2,
                        "time_closest_to_ball": 235.2,
                        "time_farthest_from_ball": 199.5,
                        "percent_defensive_third": 50.32481,
                        "percent_offensive_third": 18.613705,
                        "percent_neutral_third": 31.061481,
                        "percent_defensive_half": 67.53577,
                        "percent_offensive_half": 32.464237,
                        "percent_behind_ball": 81.867096,
                        "percent_infront_ball": 18.132902,
                        "percent_most_back": 50.568142,
                        "percent_most_forward": 49.600113,
                        "percent_closest_to_ball": 54.209785,
                        "percent_farthest_from_ball": 45.981514
                    },
                    "demo": {
                        "inflicted": 0,
                        "taken": 0
                    }
                }
            },
            {
                "start_time": 0,
                "end_time": 457.87103,
                "name": "tate <3",
                "id": {
                    "platform": "steam",
                    "id": "76561198375239232"
                },
                "rank": {
                    "id": "supersonic-legend",
                    "tier": 22,
                    "name": "Supersonic Legend"
                },
                "car_id": 23,
                "car_name": "Octane",
                "camera": {
                    "fov": 110,
                    "height": 90,
                    "pitch": -3,
                    "distance": 270,
                    "stiffness": 0.45,
                    "swivel_speed": 6.2,
                    "transition_speed": 1.3
                },
                "steering_sensitivity": 1.5,
                "stats": {
                    "core": {
                        "shots": 3,
                        "shots_against": 9,
                        "goals": 0,
                        "goals_against": 3,
                        "saves": 4,
                        "assists": 3,
                        "score": 570,
                        "mvp": false,
                        "shooting_percentage": 0
                    },
                    "boost": {
                        "bpm": 423,
                        "bcpm": 438.10358,
                        "avg_amount": 44.67,
                        "amount_collected": 3168,
                        "amount_stolen": 641,
                        "amount_collected_big": 2285,
                        "amount_stolen_big": 399,
                        "amount_collected_small": 883,
                        "amount_stolen_small": 242,
                        "count_collected_big": 27,
                        "count_stolen_big": 4,
                        "count_collected_small": 79,
                        "count_stolen_small": 22,
                        "amount_overfill": 350,
                        "amount_overfill_stolen": 7,
                        "amount_used_while_supersonic": 550,
                        "time_zero_boost": 45.63,
                        "percent_zero_boost": 10.516975,
                        "time_full_boost": 31.39,
                        "percent_full_boost": 7.234886,
                        "time_boost_0_25": 164.91,
                        "time_boost_25_50": 102.89,
                        "time_boost_50_75": 89.82,
                        "time_boost_75_100": 91.9,
                        "percent_boost_0_25": 36.6858,
                        "percent_boost_25_50": 22.88886,
                        "percent_boost_50_75": 19.981314,
                        "percent_boost_75_100": 20.444029
                    },
                    "movement": {
                        "avg_speed": 1448,
                        "total_distance": 612229,
                        "time_supersonic_speed": 71.49,
                        "time_boost_speed": 140.03,
                        "time_slow_speed": 245.3,
                        "time_ground": 275.39,
                        "time_low_air": 151.34,
                        "time_high_air": 30.09,
                        "time_powerslide": 12.01,
                        "count_powerslide": 69,
                        "avg_powerslide_duration": 0.17,
                        "avg_speed_percentage": 62.95652,
                        "percent_slow_speed": 53.697296,
                        "percent_boost_speed": 30.653212,
                        "percent_supersonic_speed": 15.649489,
                        "percent_ground": 60.28414,
                        "percent_low_air": 33.12902,
                        "percent_high_air": 6.586839
                    },
                    "positioning": {
                        "avg_distance_to_ball": 2649,
                        "avg_distance_to_ball_possession": 2552,
                        "avg_distance_to_ball_no_possession": 2688,
                        "avg_distance_to_mates": 3034,
                        "time_defensive_third": 228.3,
                        "time_neutral_third": 149.29,
                        "time_offensive_third": 79.23,
                        "time_defensive_half": 301.66,
                        "time_offensive_half": 155.16,
                        "time_behind_ball": 344.51,
                        "time_infront_ball": 112.3,
                        "time_most_back": 216.9,
                        "time_most_forward": 217,
                        "goals_against_while_last_defender": 1,
                        "time_closest_to_ball": 197.2,
                        "time_farthest_from_ball": 236.6,
                        "percent_defensive_third": 49.975918,
                        "percent_offensive_third": 17.343813,
                        "percent_neutral_third": 32.680264,
                        "percent_defensive_half": 66.03476,
                        "percent_offensive_half": 33.965237,
                        "percent_behind_ball": 75.41647,
                        "percent_infront_ball": 24.583525,
                        "percent_most_back": 49.991932,
                        "percent_most_forward": 50.01498,
                        "percent_closest_to_ball": 45.451405,
                        "percent_farthest_from_ball": 54.532463
                    },
                    "demo": {
                        "inflicted": 2,
                        "taken": 0
                    }
                }
            }
        ],
        "stats": {
            "ball": {
                "possession_time": 151.5,
                "time_in_side": 230.53
            },
            "core": {
                "shots": 12,
                "shots_against": 9,
                "goals": 4,
                "goals_against": 3,
                "saves": 6,
                "assists": 3,
                "score": 1583,
                "shooting_percentage": 33.333332
            },
            "boost": {
                "bpm": 915,
                "bcpm": 904.83325,
                "avg_amount": 92.99,
                "amount_collected": 6543,
                "amount_stolen": 1174,
                "amount_collected_big": 4685,
                "amount_stolen_big": 703,
                "amount_collected_small": 1858,
                "amount_stolen_small": 471,
                "count_collected_big": 56,
                "count_stolen_big": 8,
                "count_collected_small": 167,
                "count_stolen_small": 44,
                "amount_overfill": 862,
                "amount_overfill_stolen": 102,
                "amount_used_while_supersonic": 1339,
                "time_zero_boost": 100.229996,
                "time_full_boost": 82.21,
                "time_boost_0_25": 316.21002,
                "time_boost_25_50": 211.35,
                "time_boost_50_75": 169.78,
                "time_boost_75_100": 190.51001
            },
            "movement": {
                "total_distance": 1292216,
                "time_supersonic_speed": 153.39,
                "time_boost_speed": 331.91998,
                "time_slow_speed": 428.69,
                "time_ground": 555.23,
                "time_low_air": 301.72998,
                "time_high_air": 57.05,
                "time_powerslide": 19.67,
                "count_powerslide": 127
            },
            "positioning": {
                "time_defensive_third": 458.38,
                "time_neutral_third": 291.3,
                "time_offensive_third": 164.33,
                "time_defensive_half": 610.42004,
                "time_offensive_half": 303.58002,
                "time_behind_ball": 718.79004,
                "time_infront_ball": 195.20001
            },
            "demo": {
                "inflicted": 2,
                "taken": 0
            }
        }
    },
    "orange": {
        "color": "orange",
        "players": [
            {
                "start_time": 0,
                "end_time": 457.87103,
                "name": "Tr3bla",
                "id": {
                    "platform": "steam",
                    "id": "76561198406569848"
                },
                "rank": {
                    "id": "supersonic-legend",
                    "tier": 22,
                    "name": "Supersonic Legend"
                },
                "car_id": 4284,
                "car_name": "Fennec",
                "camera": {
                    "fov": 110,
                    "height": 100,
                    "pitch": -3,
                    "distance": 270,
                    "stiffness": 0.35,
                    "swivel_speed": 5,
                    "transition_speed": 1.7
                },
                "steering_sensitivity": 1.5,
                "stats": {
                    "core": {
                        "shots": 4,
                        "shots_against": 12,
                        "goals": 2,
                        "goals_against": 4,
                        "saves": 2,
                        "assists": 0,
                        "score": 620,
                        "mvp": false,
                        "shooting_percentage": 50
                    },
                    "boost": {
                        "bpm": 472,
                        "bcpm": 481.25015,
                        "avg_amount": 49.48,
                        "amount_collected": 3480,
                        "amount_stolen": 368,
                        "amount_collected_big": 2683,
                        "amount_stolen_big": 148,
                        "amount_collected_small": 797,
                        "amount_stolen_small": 220,
                        "count_collected_big": 32,
                        "count_stolen_big": 2,
                        "count_collected_small": 61,
                        "count_stolen_small": 16,
                        "amount_overfill": 412,
                        "amount_overfill_stolen": 25,
                        "amount_used_while_supersonic": 282,
                        "time_zero_boost": 35.97,
                        "percent_zero_boost": 8.290502,
                        "time_full_boost": 91.77,
                        "percent_full_boost": 21.151497,
                        "time_boost_0_25": 120.75,
                        "time_boost_25_50": 96.25,
                        "time_boost_50_75": 61.91,
                        "time_boost_75_100": 156.31,
                        "percent_boost_0_25": 27.744589,
                        "percent_boost_25_50": 22.115252,
                        "percent_boost_50_75": 14.22499,
                        "percent_boost_75_100": 35.91517
                    },
                    "movement": {
                        "avg_speed": 1657,
                        "total_distance": 695145,
                        "time_supersonic_speed": 96.7,
                        "time_boost_speed": 185.28,
                        "time_slow_speed": 168.98,
                        "time_ground": 185.37,
                        "time_low_air": 211.01,
                        "time_high_air": 54.58,
                        "time_powerslide": 7.55,
                        "count_powerslide": 104,
                        "avg_powerslide_duration": 0.07,
                        "avg_speed_percentage": 72.04348,
                        "percent_slow_speed": 37.471172,
                        "percent_boost_speed": 41.085682,
                        "percent_supersonic_speed": 21.443142,
                        "percent_ground": 41.10564,
                        "percent_low_air": 46.791286,
                        "percent_high_air": 12.103068
                    },
                    "positioning": {
                        "avg_distance_to_ball": 2362,
                        "avg_distance_to_ball_possession": 2119,
                        "avg_distance_to_ball_no_possession": 2672,
                        "avg_distance_to_mates": 3008,
                        "time_defensive_third": 195.91,
                        "time_neutral_third": 164.6,
                        "time_offensive_third": 90.46,
                        "time_defensive_half": 286.62,
                        "time_offensive_half": 164.34,
                        "time_behind_ball": 341.98,
                        "time_infront_ball": 108.98,
                        "time_most_back": 203.3,
                        "time_most_forward": 230.5,
                        "goals_against_while_last_defender": 1,
                        "time_closest_to_ball": 218.2,
                        "time_farthest_from_ball": 215.6,
                        "percent_defensive_third": 43.441914,
                        "percent_offensive_third": 20.058985,
                        "percent_neutral_third": 36.499104,
                        "percent_defensive_half": 63.557743,
                        "percent_offensive_half": 36.442257,
                        "percent_behind_ball": 75.83377,
                        "percent_infront_ball": 24.166222,
                        "percent_most_back": 46.857353,
                        "percent_most_forward": 53.126514,
                        "percent_closest_to_ball": 50.29156,
                        "percent_farthest_from_ball": 49.692307
                    },
                    "demo": {
                        "inflicted": 0,
                        "taken": 2
                    }
                }
            },
            {
                "start_time": 0,
                "end_time": 457.87103,
                "name": "Ervinnxi.",
                "id": {
                    "platform": "epic",
                    "id": "53bac92813824d91a4f0f6c321d50e69"
                },
                "rank": {
                    "id": "supersonic-legend",
                    "tier": 22,
                    "name": "Supersonic Legend"
                },
                "car_id": 4284,
                "car_name": "Fennec",
                "camera": {
                    "fov": 110,
                    "height": 100,
                    "pitch": -3,
                    "distance": 270,
                    "stiffness": 0.35,
                    "swivel_speed": 3,
                    "transition_speed": 1.5
                },
                "steering_sensitivity": 1.55,
                "stats": {
                    "core": {
                        "shots": 5,
                        "shots_against": 12,
                        "goals": 1,
                        "goals_against": 4,
                        "saves": 3,
                        "assists": 1,
                        "score": 553,
                        "mvp": false,
                        "shooting_percentage": 20
                    },
                    "boost": {
                        "bpm": 451,
                        "bcpm": 453.31552,
                        "avg_amount": 46.66,
                        "amount_collected": 3278,
                        "amount_stolen": 672,
                        "amount_collected_big": 2102,
                        "amount_stolen_big": 296,
                        "amount_collected_small": 1176,
                        "amount_stolen_small": 376,
                        "count_collected_big": 23,
                        "count_stolen_big": 3,
                        "count_collected_small": 85,
                        "count_stolen_small": 28,
                        "amount_overfill": 218,
                        "amount_overfill_stolen": 34,
                        "amount_used_while_supersonic": 399,
                        "time_zero_boost": 47.34,
                        "percent_zero_boost": 10.911102,
                        "time_full_boost": 37.96,
                        "percent_full_boost": 8.749165,
                        "time_boost_0_25": 157.82,
                        "time_boost_25_50": 93.01,
                        "time_boost_50_75": 64.9,
                        "time_boost_75_100": 129.01,
                        "percent_boost_0_25": 35.485905,
                        "percent_boost_25_50": 20.913343,
                        "percent_boost_50_75": 14.592796,
                        "percent_boost_75_100": 29.007957
                    },
                    "movement": {
                        "avg_speed": 1482,
                        "total_distance": 631398,
                        "time_supersonic_speed": 67.63,
                        "time_boost_speed": 160.17,
                        "time_slow_speed": 229.25,
                        "time_ground": 236.56,
                        "time_low_air": 189.44,
                        "time_high_air": 31.04,
                        "time_powerslide": 9.49,
                        "count_powerslide": 70,
                        "avg_powerslide_duration": 0.14,
                        "avg_speed_percentage": 64.434784,
                        "percent_slow_speed": 50.158627,
                        "percent_boost_speed": 35.044308,
                        "percent_supersonic_speed": 14.797068,
                        "percent_ground": 51.759144,
                        "percent_low_air": 41.449326,
                        "percent_high_air": 6.7915277
                    },
                    "positioning": {
                        "avg_distance_to_ball": 2269,
                        "avg_distance_to_ball_possession": 2121,
                        "avg_distance_to_ball_no_possession": 2470,
                        "avg_distance_to_mates": 3008,
                        "time_defensive_third": 209.27,
                        "time_neutral_third": 153.28,
                        "time_offensive_third": 94.49,
                        "time_defensive_half": 288.11,
                        "time_offensive_half": 168.93,
                        "time_behind_ball": 353.07,
                        "time_infront_ball": 103.97,
                        "time_most_back": 238.4,
                        "time_most_forward": 202.9,
                        "goals_against_while_last_defender": 3,
                        "time_closest_to_ball": 216.3,
                        "time_farthest_from_ball": 225,
                        "percent_defensive_third": 45.788113,
                        "percent_offensive_third": 20.67434,
                        "percent_neutral_third": 33.537544,
                        "percent_defensive_half": 63.038246,
                        "percent_offensive_half": 36.961754,
                        "percent_behind_ball": 77.25144,
                        "percent_infront_ball": 22.748556,
                        "percent_most_back": 54.947334,
                        "percent_most_forward": 46.76516,
                        "percent_closest_to_ball": 49.85364,
                        "percent_farthest_from_ball": 51.858852
                    },
                    "demo": {
                        "inflicted": 0,
                        "taken": 0
                    }
                }
            }
        ],
        "stats": {
            "ball": {
                "possession_time": 212.65,
                "time_in_side": 191.19
            },
            "core": {
                "shots": 9,
                "shots_against": 12,
                "goals": 3,
                "goals_against": 4,
                "saves": 5,
                "assists": 1,
                "score": 1173,
                "shooting_percentage": 33.333332
            },
            "boost": {
                "bpm": 923,
                "bcpm": 934.5657,
                "avg_amount": 96.14,
                "amount_collected": 6758,
                "amount_stolen": 1040,
                "amount_collected_big": 4785,
                "amount_stolen_big": 444,
                "amount_collected_small": 1973,
                "amount_stolen_small": 596,
                "count_collected_big": 55,
                "count_stolen_big": 5,
                "count_collected_small": 146,
                "count_stolen_small": 44,
                "amount_overfill": 630,
                "amount_overfill_stolen": 59,
                "amount_used_while_supersonic": 681,
                "time_zero_boost": 83.31,
                "time_full_boost": 129.73,
                "time_boost_0_25": 278.57,
                "time_boost_25_50": 189.26001,
                "time_boost_50_75": 126.81,
                "time_boost_75_100": 285.32
            },
            "movement": {
                "total_distance": 1326543,
                "time_supersonic_speed": 164.32999,
                "time_boost_speed": 345.45,
                "time_slow_speed": 398.22998,
                "time_ground": 421.93,
                "time_low_air": 400.45,
                "time_high_air": 85.62,
                "time_powerslide": 17.04,
                "count_powerslide": 174
            },
            "positioning": {
                "time_defensive_third": 405.18,
                "time_neutral_third": 317.88,
                "time_offensive_third": 184.95,
                "time_defensive_half": 574.73,
                "time_offensive_half": 333.27,
                "time_behind_ball": 695.05005,
                "time_infront_ball": 212.95001
            },
            "demo": {
                "inflicted": 0,
                "taken": 2
            }
        }
    },
    "playlist_name": "Ranked Doubles",
    "map_name": "DFH Stadium (Stormy)",
    "server": {
        "name": "EU545-Nano11",
        "region": "EU"
    }
}