{
    "id": "612c872a-6b16-4b1d-9016-6db30fcd0e2f",
    "link": "https://ballchasing.com/api/replays/612c872a-6b16-4b1d-9016-6db30fcd0e2f",
    "created": "2023-09-20T17:42:35.767376Z",
    "uploader": {
        "steam_id": "76561198352901751",
        "name": "Krazy",
        "profile_url": "https://steamcommunity.com/profiles/76561198352901751/",
        "avatar": "https://avatars.steamstatic.com/173c9835e70f2e0a24130a47ef6ce6706468aebd.jpg"
    },
    "status": "ok",
    "rocket_league_id": "B1347E054871ED4D1CC62CA28A50C4DA",
    "match_guid": "1587996E11EE57DC0BA8568A80B43590",
    "title": "2023-09-20.19.42 OhNoKhaliD Ranked Doubles Loss",
    "map_code": "farm_night_p",
    "match_type": "Online",
    "team_size": 2,
    "playlist_id": "ranked-doubles",
    "duration": 396,
    "overtime": true,
    "overtime_seconds": 43,
    "season": 12,
    "season_type": "free2play",
    "date": "2023-09-20T19:42:35+02:00",
    "date_has_timezone": true,
    "visibility": "public",
    "min_rank": {
        "id": "champion-2",
        "tier": 17,
        "division": 1,
        "name": "Champion II Division 1"
    },
    "max_rank": {
        "id": "champion-3",
        "tier": 18,
        "division": 2,
        "name": "Champion III Division 2"
    },
    "blue": {
        "color": "blue",
        "players": [
            {
                "start_time": 0,
                "end_time": 396.6003,
                "name": "Daeky.",
                "id": {
                    "platform": "epic",
                    "id": "9335791117b144d8a3ae7534d9899b97"
                },
                "mvp": true,
                "rank": {
                    "id": "champion-3",
                    "tier": 18,
                    "division": 1,
                    "name": "Champion III Division 1"
                },
                "car_id": 4284,
                "car_name": "Fennec",
                "camera": {
                    "fov": 110,
                    "height": 100,
                    "pitch": -5,
                    "distance": 270,
                    "stiffness": 0.4,
                    "swivel_speed": 6.8,
                    "transition_speed": 1.2
                },
                "steering_sensitivity": 2.49,
                "stats": {
                    "core": {
                        "shots": 4,
                        "shots_against": 11,
                        "goals": 2,
                        "goals_against": 2,
                        "saves": 3,
                        "assists": 0,
                        "score": 635,
                        "mvp": true,
                        "shooting_percentage": 50
                    },
                    "boost": {
                        "bpm": 364,
                        "bcpm": 369.25516,
                        "avg_amount": 43.28,
                        "amount_collected": 2330,
                        "amount_stolen": 670,
                        "amount_collected_big": 1525,
                        "amount_stolen_big": 381,
                        "amount_collected_small": 805,
                        "amount_stolen_small": 289,
                        "count_collected_big": 18,
                        "count_stolen_big": 4,
                        "count_collected_small": 65,
                        "count_stolen_small": 20,
                        "amount_overfill": 276,
                        "amount_overfill_stolen": 18,
                        "amount_used_while_supersonic": 420,
                        "time_zero_boost": 57.72,
                        "percent_zero_boost": 15.245642,
                        "time_full_boost": 37.55,
                        "percent_full_boost": 9.918119,
                        "time_boost_0_25": 127.24,
                        "time_boost_25_50": 111.3,
                        "time_boost_50_75": 83.38,
                        "time_boost_75_100": 65.54,
                        "percent_boost_0_25": 32.839516,
                        "percent_boost_25_50": 28.725544,
                        "percent_boost_50_75": 21.51964,
                        "percent_boost_75_100": 16.915293
                    },
                    "movement": {
                        "avg_speed": 1452,
                        "total_distance": 544886,
                        "time_supersonic_speed": 61.5,
                        "time_boost_speed": 132.22,
                        "time_slow_speed": 202.68,
                        "time_ground": 201.68,
                        "time_low_air": 178.83,
                        "time_high_air": 15.9,
                        "time_powerslide": 4.3,
                        "count_powerslide": 37,
                        "avg_powerslide_duration": 0.12,
                        "avg_speed_percentage": 63.130436,
                        "percent_slow_speed": 51.130173,
                        "percent_boost_speed": 33.355198,
                        "percent_supersonic_speed": 15.514632,
                        "percent_ground": 50.876617,
                        "percent_low_air": 45.112385,
                        "percent_high_air": 4.0109987
                    },
                    "positioning": {
                        "avg_distance_to_ball": 1963,
                        "avg_distance_to_ball_possession": 1804,
                        "avg_distance_to_ball_no_possession": 2106,
                        "avg_distance_to_mates": 2725,
                        "time_defensive_third": 198.48,
                        "time_neutral_third": 121.33,
                        "time_offensive_third": 76.59,
                        "time_defensive_half": 266.34,
                        "time_offensive_half": 130.06,
                        "time_behind_ball": 289.28,
                        "time_infront_ball": 107.12,
                        "time_most_back": 187.8,
                        "time_most_forward": 187.7,
                        "time_closest_to_ball": 192.6,
                        "time_farthest_from_ball": 182.9,
                        "percent_defensive_third": 50.070633,
                        "percent_offensive_third": 19.32139,
                        "percent_neutral_third": 30.60797,
                        "percent_defensive_half": 67.189705,
                        "percent_offensive_half": 32.81029,
                        "percent_behind_ball": 72.97679,
                        "percent_infront_ball": 27.023209,
                        "percent_most_back": 49.6038,
                        "percent_most_forward": 49.57739,
                        "percent_closest_to_ball": 50.87163,
                        "percent_farthest_from_ball": 48.30956
                    },
                    "demo": {
                        "inflicted": 3,
                        "taken": 0
                    }
                }
            },
            {
                "start_time": 0,
                "end_time": 396.6003,
                "name": "Bablo",
                "id": {
                    "platform": "steam",
                    "id": "76561198844015935"
                },
                "rank": {
                    "id": "champion-2",
                    "tier": 17,
                    "division": 1,
                    "name": "Champion II Division 1"
                },
                "car_id": 3265,
                "car_name": "McLaren 570S",
                "camera": {
                    "fov": 110,
                    "height": 110,
                    "pitch": -3,
                    "distance": 270,
                    "stiffness": 0.45,
                    "swivel_speed": 5,
                    "transition_speed": 1
                },
                "steering_sensitivity": 1,
                "stats": {
                    "core": {
                        "shots": 3,
                        "shots_against": 11,
                        "goals": 1,
                        "goals_against": 2,
                        "saves": 3,
                        "assists": 2,
                        "score": 577,
                        "mvp": false,
                        "shooting_percentage": 33.333332
                    },
                    "boost": {
                        "bpm": 378,
                        "bcpm": 394.92868,
                        "avg_amount": 48.6,
                        "amount_collected": 2492,
                        "amount_stolen": 684,
                        "amount_collected_big": 2046,
                        "amount_stolen_big": 575,
                        "amount_collected_small": 446,
                        "amount_stolen_small": 109,
                        "count_collected_big": 26,
                        "count_stolen_big": 6,
                        "count_collected_small": 39,
                        "count_stolen_small": 10,
                        "amount_overfill": 471,
                        "amount_overfill_stolen": 24,
                        "amount_used_while_supersonic": 480,
                        "time_zero_boost": 58.09,
                        "percent_zero_boost": 15.34337,
                        "time_full_boost": 87.05,
                        "percent_full_boost": 22.992603,
                        "time_boost_0_25": 114.17,
                        "time_boost_25_50": 77.48,
                        "time_boost_50_75": 64.15,
                        "time_boost_75_100": 121.34,
                        "percent_boost_0_25": 30.27258,
                        "percent_boost_25_50": 20.544098,
                        "percent_boost_50_75": 17.0096,
                        "percent_boost_75_100": 32.17373
                    },
                    "movement": {
                        "avg_speed": 1450,
                        "total_distance": 532419,
                        "time_supersonic_speed": 44.53,
                        "time_boost_speed": 134.56,
                        "time_slow_speed": 212.07,
                        "time_ground": 240.34,
                        "time_low_air": 136.76,
                        "time_high_air": 14.06,
                        "time_powerslide": 9.53,
                        "count_powerslide": 73,
                        "avg_powerslide_duration": 0.13,
                        "avg_speed_percentage": 63.04348,
                        "percent_slow_speed": 54.215664,
                        "percent_boost_speed": 34.400246,
                        "percent_supersonic_speed": 11.3840885,
                        "percent_ground": 61.44289,
                        "percent_low_air": 34.962673,
                        "percent_high_air": 3.5944374
                    },
                    "positioning": {
                        "avg_distance_to_ball": 2067,
                        "avg_distance_to_ball_possession": 1764,
                        "avg_distance_to_ball_no_possession": 2319,
                        "avg_distance_to_mates": 2725,
                        "time_defensive_third": 221.76,
                        "time_neutral_third": 101.42,
                        "time_offensive_third": 67.99,
                        "time_defensive_half": 273.97,
                        "time_offensive_half": 117.2,
                        "time_behind_ball": 290.93,
                        "time_infront_ball": 100.24,
                        "time_most_back": 191.5,
                        "time_most_forward": 183.6,
                        "goals_against_while_last_defender": 2,
                        "time_closest_to_ball": 178.8,
                        "time_farthest_from_ball": 196.3,
                        "percent_defensive_third": 56.691467,
                        "percent_offensive_third": 17.381191,
                        "percent_neutral_third": 25.927347,
                        "percent_defensive_half": 70.038605,
                        "percent_offensive_half": 29.9614,
                        "percent_behind_ball": 74.37431,
                        "percent_infront_ball": 25.625689,
                        "percent_most_back": 50.58109,
                        "percent_most_forward": 48.494453,
                        "percent_closest_to_ball": 47.226624,
                        "percent_farthest_from_ball": 51.848915
                    },
                    "demo": {
                        "inflicted": 1,
                        "taken": 1
                    }
                }
            }
        ],
        "stats": {
            "ball": {
                "possession_time": 151.66,
                "time_in_side": 217.42
            },
            "core": {
                "shots": 7,
                "shots_against": 11,
                "goals": 3,
                "goals_against": 2,
                "saves": 6,
                "assists": 2,
                "score": 1212,
                "shooting_percentage": 42.857143
            },
            "boost": {
                "bpm": 742,
                "bcpm": 764.18384,
                "avg_amount": 91.88,
                "amount_collected": 4822,
                "amount_stolen": 1354,
                "amount_collected_big": 3571,
                "amount_stolen_big": 956,
                "amount_collected_small": 1251,
                "amount_stolen_small": 398,
                "count_collected_big": 44,
                "count_stolen_big": 10,
                "count_collected_small": 104,
                "count_stolen_small": 30,
                "amount_overfill": 747,
                "amount_overfill_stolen": 42,
                "amount_used_while_supersonic": 900,
                "time_zero_boost": 115.81,
                "time_full_boost": 124.600006,
                "time_boost_0_25": 241.41,
                "time_boost_25_50": 188.78,
                "time_boost_50_75": 147.53,
                "time_boost_75_100": 186.88
            },
            "movement": {
                "total_distance": 1077305,
                "time_supersonic_speed": 106.03,
                "time_boost_speed": 266.78,
                "time_slow_speed": 414.75,
                "time_ground": 442.02,
                "time_low_air": 315.59,
                "time_high_air": 29.96,
                "time_powerslide": 13.83,
                "count_powerslide": 110
            },
            "positioning": {
                "time_defensive_third": 420.24,
                "time_neutral_third": 222.75,
                "time_offensive_third": 144.57999,
                "time_defensive_half": 540.31,
                "time_offensive_half": 247.26,
                "time_behind_ball": 580.20996,
                "time_infront_ball": 207.36
            },
            "demo": {
                "inflicted": 4,
                "taken": 1
            }
        }
    },
    "orange": {
        "color": "orange",
        "players": [
            {
                "start_time": 0,
                "end_time": 396.6003,
                "name": "OhNoKhaliD",
                "id": {
                    "platform": "epic",
                    "id": "ca371382286a414c8cbedd0e55b76b6a"
                },
                "rank": {
                    "id": "champion-3",
                    "tier": 18,
                    "division": 2,
                    "name": "Champion III Division 2"
                },
                "car_id": 4284,
                "car_name": "Fennec",
                "camera": {
                    "fov": 110,
                    "height": 90,
                    "pitch": -5,
                    "distance": 270,
                    "stiffness": 0.35,
                    "swivel_speed": 6,
                    "transition_speed": 1.4
                },
                "steering_sensitivity": 1,
                "stats": {
                    "core": {
                        "shots": 6,
                        "shots_against": 7,
                        "goals": 1,
                        "goals_against": 3,
                        "saves": 2,
                        "assists": 0,
                        "score": 416,
                        "mvp": false,
                        "shooting_percentage": 16.666666
                    },
                    "boost": {
                        "bpm": 397,
                        "bcpm": 380.19016,
                        "avg_amount": 56.54,
                        "amount_collected": 2399,
                        "amount_stolen": 499,
                        "amount_collected_big": 1616,
                        "amount_stolen_big": 290,
                        "amount_collected_small": 783,
                        "amount_stolen_small": 209,
                        "count_collected_big": 23,
                        "count_stolen_big": 5,
                        "count_collected_small": 62,
                        "count_stolen_small": 20,
                        "amount_overfill": 491,
                        "amount_overfill_stolen": 169,
                        "amount_used_while_supersonic": 258,
                        "time_zero_boost": 55.66,
                        "percent_zero_boost": 14.701531,
                        "time_full_boost": 39.1,
                        "percent_full_boost": 10.327521,
                        "time_boost_0_25": 121.69,
                        "time_boost_25_50": 60.48,
                        "time_boost_50_75": 61.96,
                        "time_boost_75_100": 123.09,
                        "percent_boost_0_25": 33.138172,
                        "percent_boost_25_50": 16.46969,
                        "percent_boost_50_75": 16.872719,
                        "percent_boost_75_100": 33.519417
                    },
                    "movement": {
                        "avg_speed": 1497,
                        "total_distance": 543203,
                        "time_supersonic_speed": 61.32,
                        "time_boost_speed": 134.88,
                        "time_slow_speed": 188.06,
                        "time_ground": 204.08,
                        "time_low_air": 158.45,
                        "time_high_air": 21.73,
                        "time_powerslide": 3.76,
                        "count_powerslide": 33,
                        "avg_powerslide_duration": 0.11,
                        "avg_speed_percentage": 65.08696,
                        "percent_slow_speed": 48.94082,
                        "percent_boost_speed": 35.101234,
                        "percent_supersonic_speed": 15.957945,
                        "percent_ground": 53.10987,
                        "percent_low_air": 41.2351,
                        "percent_high_air": 5.655025
                    },
                    "positioning": {
                        "avg_distance_to_ball": 2072,
                        "avg_distance_to_ball_possession": 1811,
                        "avg_distance_to_ball_no_possession": 2387,
                        "avg_distance_to_mates": 2906,
                        "time_defensive_third": 157.94,
                        "time_neutral_third": 115.28,
                        "time_offensive_third": 111.04,
                        "time_defensive_half": 221.06,
                        "time_offensive_half": 163.2,
                        "time_behind_ball": 283.58,
                        "time_infront_ball": 100.68,
                        "time_most_back": 165.6,
                        "time_most_forward": 205.8,
                        "goals_against_while_last_defender": 3,
                        "time_closest_to_ball": 221.9,
                        "time_farthest_from_ball": 149.5,
                        "percent_defensive_third": 41.10238,
                        "percent_offensive_third": 28.8971,
                        "percent_neutral_third": 30.000519,
                        "percent_defensive_half": 57.528755,
                        "percent_offensive_half": 42.47124,
                        "percent_behind_ball": 73.79899,
                        "percent_infront_ball": 26.201012,
                        "percent_most_back": 43.740093,
                        "percent_most_forward": 54.358162,
                        "percent_closest_to_ball": 58.61067,
                        "percent_farthest_from_ball": 39.487587
                    },
                    "demo": {
                        "inflicted": 1,
                        "taken": 4
                    }
                }
            },
            {
                "start_time": 0,
                "end_time": 396.6003,
                "name": "pepis",
                "id": {
                    "platform": "steam",
                    "id": "76561198236938208"
                },
                "rank": {
                    "id": "champion-3",
                    "tier": 18,
                    "division": 1,
                    "name": "Champion III Division 1"
                },
                "car_id": 4284,
                "car_name": "Fennec",
                "camera": {
                    "fov": 110,
                    "height": 90,
                    "pitch": -5,
                    "distance": 270,
                    "stiffness": 0.35,
                    "swivel_speed": 10,
                    "transition_speed": 1
                },
                "steering_sensitivity": 1,
                "stats": {
                    "core": {
                        "shots": 5,
                        "shots_against": 7,
                        "goals": 1,
                        "goals_against": 3,
                        "saves": 0,
                        "assists": 0,
                        "score": 350,
                        "mvp": false,
                        "shooting_percentage": 20
                    },
                    "boost": {
                        "bpm": 313,
                        "bcpm": 301.4263,
                        "avg_amount": 47.21,
                        "amount_collected": 1902,
                        "amount_stolen": 399,
                        "amount_collected_big": 1147,
                        "amount_stolen_big": 200,
                        "amount_collected_small": 755,
                        "amount_stolen_small": 199,
                        "count_collected_big": 13,
                        "count_stolen_big": 2,
                        "count_collected_small": 65,
                        "count_stolen_small": 18,
                        "amount_overfill": 174,
                        "amount_overfill_stolen": 14,
                        "amount_used_while_supersonic": 134,
                        "time_zero_boost": 41.92,
                        "percent_zero_boost": 11.0723715,
                        "time_full_boost": 41.21,
                        "percent_full_boost": 10.884839,
                        "time_boost_0_25": 135.9,
                        "time_boost_25_50": 78.79,
                        "time_boost_50_75": 65.19,
                        "time_boost_75_100": 94.41,
                        "percent_boost_0_25": 36.308743,
                        "percent_boost_25_50": 21.050522,
                        "percent_boost_50_75": 17.416975,
                        "percent_boost_75_100": 25.223757
                    },
                    "movement": {
                        "avg_speed": 1418,
                        "total_distance": 527857,
                        "time_supersonic_speed": 28.57,
                        "time_boost_speed": 148.38,
                        "time_slow_speed": 219.49,
                        "time_ground": 246.24,
                        "time_low_air": 136.35,
                        "time_high_air": 13.85,
                        "time_powerslide": 6.11,
                        "count_powerslide": 56,
                        "avg_powerslide_duration": 0.11,
                        "avg_speed_percentage": 61.652172,
                        "percent_slow_speed": 55.36525,
                        "percent_boost_speed": 37.42811,
                        "percent_supersonic_speed": 7.206639,
                        "percent_ground": 62.1128,
                        "percent_low_air": 34.393604,
                        "percent_high_air": 3.4935927
                    },
                    "positioning": {
                        "avg_distance_to_ball": 2412,
                        "avg_distance_to_ball_possession": 2387,
                        "avg_distance_to_ball_no_possession": 2406,
                        "avg_distance_to_mates": 2906,
                        "time_defensive_third": 158.7,
                        "time_neutral_third": 140.5,
                        "time_offensive_third": 97.24,
                        "time_defensive_half": 223.12,
                        "time_offensive_half": 173.31,
                        "time_behind_ball": 306.93,
                        "time_infront_ball": 89.51,
                        "time_most_back": 211.5,
                        "time_most_forward": 171.3,
                        "time_closest_to_ball": 149.5,
                        "time_farthest_from_ball": 233.3,
                        "percent_defensive_third": 40.031277,
                        "percent_offensive_third": 24.528301,
                        "percent_neutral_third": 35.44042,
                        "percent_defensive_half": 56.282322,
                        "percent_offensive_half": 43.71768,
                        "percent_behind_ball": 77.421555,
                        "percent_infront_ball": 22.578447,
                        "percent_most_back": 55.86371,
                        "percent_most_forward": 45.24564,
                        "percent_closest_to_ball": 39.487587,
                        "percent_farthest_from_ball": 61.621765
                    },
                    "demo": {
                        "inflicted": 0,
                        "taken": 0
                    }
                }
            }
        ],
        "stats": {
            "ball": {
                "possession_time": 175.62,
                "time_in_side": 153.56
            },
            "core": {
                "shots": 11,
                "shots_against": 7,
                "goals": 2,
                "goals_against": 3,
                "saves": 2,
                "assists": 0,
                "score": 766,
                "shooting_percentage": 18.181818
            },
            "boost": {
                "bpm": 710,
                "bcpm": 681.61646,
                "avg_amount": 103.75,
                "amount_collected": 4301,
                "amount_stolen": 898,
                "amount_collected_big": 2763,
                "amount_stolen_big": 490,
                "amount_collected_small": 1538,
                "amount_stolen_small": 408,
                "count_collected_big": 36,
                "count_stolen_big": 7,
                "count_collected_small": 127,
                "count_stolen_small": 38,
                "amount_overfill": 665,
                "amount_overfill_stolen": 183,
                "amount_used_while_supersonic": 392,
                "time_zero_boost": 97.58,
                "time_full_boost": 80.31,
                "time_boost_0_25": 257.59,
                "time_boost_25_50": 139.27,
                "time_boost_50_75": 127.15,
                "time_boost_75_100": 217.5
            },
            "movement": {
                "total_distance": 1071060,
                "time_supersonic_speed": 89.89,
                "time_boost_speed": 283.26,
                "time_slow_speed": 407.55,
                "time_ground": 450.32,
                "time_low_air": 294.8,
                "time_high_air": 35.58,
                "time_powerslide": 9.87,
                "count_powerslide": 89
            },
            "positioning": {
                "time_defensive_third": 316.64,
                "time_neutral_third": 255.78,
                "time_offensive_third": 208.28,
                "time_defensive_half": 444.18,
                "time_offensive_half": 336.51,
                "time_behind_ball": 590.51,
                "time_infront_ball": 190.19
            },
            "demo": {
                "inflicted": 1,
                "taken": 4
            }
        }
    },
    "playlist_name": "Ranked Doubles",
    "map_name": "Farmstead (Night)",
    "server": {
        "name": "EU5210253526802716756",
        "region": "EU"
    }
}